modules/__init__.py
realtime_visualtracking-0.1.0.dist-info/LICENCE
realtime_visualtracking-0.1.0.dist-info/METADATA
realtime_visualtracking-0.1.0.dist-info/WHEEL
realtime_visualtracking-0.1.0.dist-info/top_level.txt
realtime_visualtracking-0.1.0.dist-info/RECORD
